{"is_source_file": false, "format": "", "description": "", "external_files": [], "external_methods": [], "published": [], "classes": [], "methods": [], "calls": [], "search-terms": [], "state": 2, "file_id": 1, "knowledge_revision": 114, "git_revision": "f56447114a55dd250491bf302194dff3cea1ec0d", "hash": "a25b136bcd8c830b4aca774268041854", "format-version": 4, "code-base-name": "tic_tac_toe_frontend", "filename": "tic_tac_toe_frontend/README.md", "revision_history": [{"114": "f56447114a55dd250491bf302194dff3cea1ec0d"}]}